iptw_survival/__init__.py
iptw_survival/iptw_survival_estimator.py
iptw_survival-0.1.7.dist-info/licenses/LICENSE
iptw_survival-0.1.7.dist-info/METADATA
iptw_survival-0.1.7.dist-info/WHEEL
iptw_survival-0.1.7.dist-info/top_level.txt
iptw_survival-0.1.7.dist-info/RECORD
