Metadata-Version: 2.4
Name: iptw-survival
Version: 0.1.7
Summary: A Python package for IPTW-based survival analysis with bootstrapped metrics and covariate balance diagnostics.
Author-email: Xavier Orcutt <xavierorcutt@gmail.com>
License-Expression: MIT
Project-URL: Homepage, https://github.com/xavier-orcutt/IPTWSurvivalEstimator
Project-URL: Documentation, https://github.com/xavier-orcutt/IPTWSurvivalEstimator#readme
Project-URL: Bug Tracker, https://github.com/xavier-orcutt/IPTWSurvivalEstimator/issues
Keywords: IPTW,survival analysis,causal inference,Kaplan-Meier,real-world data,oncology,EHR,propensity score,treatment effect,biostatistics,python
Classifier: Development Status :: 3 - Alpha
Classifier: Intended Audience :: Science/Research
Classifier: Intended Audience :: Healthcare Industry
Classifier: Operating System :: OS Independent
Classifier: Programming Language :: Python :: 3.13
Classifier: Topic :: Scientific/Engineering :: Information Analysis
Classifier: Topic :: Scientific/Engineering :: Bio-Informatics
Classifier: Topic :: Scientific/Engineering :: Medical Science Apps.
Classifier: Topic :: Software Development :: Libraries :: Python Modules
Requires-Python: >=3.13
License-File: LICENSE
Requires-Dist: pandas>=1.3
Requires-Dist: numpy>=1.21
Requires-Dist: matplotlib>=3.4
Requires-Dist: scikit-learn>=1.0
Requires-Dist: lifelines>=0.26
Dynamic: license-file
